jut/__init__.py
jut/cli.py
jut-0.0.24.dist-info/entry_points.txt
jut-0.0.24.dist-info/WHEEL
jut-0.0.24.dist-info/METADATA
jut-0.0.24.dist-info/RECORD
