Metadata-Version: 2.1
Name: jut
Version: 0.0.24
Summary: Render Jupyter Notebook in the terminal
Home-page: https://github.com/kracekumar/jut/
License: MIT
Author: kracekumar
Author-email: me@kracekumar.com
Requires-Python: >=3.6.1,<4.0.0
Classifier: License :: OSI Approved :: MIT License
Classifier: Programming Language :: Python :: 3
Classifier: Programming Language :: Python :: 3.7
Classifier: Programming Language :: Python :: 3.8
Classifier: Programming Language :: Python :: 3.9
Requires-Dist: click (==7.1.2)
Requires-Dist: nbformat (==5.1.2)
Requires-Dist: pydantic (==1.8.1)
Requires-Dist: rich (==9.13.0)
Project-URL: Repository, https://github.com/kracekumar/jut/
